ajson/__init__.py
ajson/aserializer.py
ajson/class_decorator.py
ajson/comment_handler.py
ajson/json_type_reports.py
ajson/regex.py
ajson/singleton.py
ajson/type_inspector.py
tests/__init__.py
tests/test_ajson_decorator.py
tests/test_class_inspector.py
tests/test_comment_handler.py
tests/test_serializer.py
tests/test_serializer_with_annotations.py
tests/resources/__init__.py
tests/types_for_tests/__init__.py
tests/types_for_tests/test_serializaer_with_annotations_types.py
ajson-0.12.0.dist-info/LICENSE
ajson-0.12.0.dist-info/METADATA
ajson-0.12.0.dist-info/WHEEL
ajson-0.12.0.dist-info/top_level.txt
ajson-0.12.0.dist-info/RECORD
