Metadata-Version: 2.1
Name: ajson
Version: 0.12.0
Summary: simple serializer based on annotations
Home-page: https://github.com/JorgeGarciaIrazabal/ajson
Author: Jorge Garcia Irazabal
Author-email: jorge.girazabal@gmail.com
License: GNU General Public License v3 (GPLv3)
Keywords: json serializer annotation validation
Platform: UNKNOWN
Classifier: Development Status :: 4 - Beta
Classifier: Intended Audience :: Developers
Classifier: Topic :: Software Development :: Build Tools
Classifier: License :: OSI Approved :: GNU General Public License v3 (GPLv3)
Classifier: Programming Language :: Python :: 3.6
Requires-Dist: beautifulsoup4
Requires-Dist: typeguard (<2.3.0,>=2.2.0)
